{"id":10185,"title":"董卿被曝怀孕 赴美学习实为待产","keywords":"董卿,怀孕,赴美,学习,实为,待产,近期,央视,一姐,董卿,离职,以来,","description":"近期，继央视一姐董卿被爆离职央视以来，关于她的各种事情便成为媒体关注的焦点，这不近日，董卿又被爆出已怀有身孕，赴美深造实为待产的绯闻，这是怎么回事儿呢？下面我们就来了解一下吧. 日前，央视当家花旦董卿因缺席央视节目的录制而引发出走传闻，她本","content":"<p>\n\t　　近期，继央视一姐董卿被爆离职央视以来，关于她的各种事情便成为媒体关注的焦点，这不近日，董卿又被爆出已怀有身孕，赴美深造实为待产的绯闻，这是怎么回事儿呢？下面我们就来了解一下吧。</p><p><img alt=\"董卿怀孕\" src=\"/uploads/73264d67fdcb307850af8d270233275b.jpg\"></p><p>\n\t　　日前，央视当家花旦董卿因缺席央视节目的录制而引发出走传闻，她本人在接受采访时称自己只是停薪留职赴美深造。央视也通过微博就“董卿辞职”传闻发表特别声明，称董卿将赴美国南加州大学深造学习，从未向央视提出过离职。不过近日有媒体获悉，董卿此次赴美虽然明为学习，但实际上是为待产。</p><p>\n\t　　13日，有关董卿未现身《我要上春晚》现场，疑似从央视离职的消息喧嚣尘上。随后董卿亲自辟谣，称自己将以美国南加州大学访问学者的身份，去美国学习深造：“人的一生总应该有所追求，不管是谁，不管在什么年龄。我不会离开央视，今后将继续做主持人。”</p><p>\n\t　　在董卿被传出欲出走央视的同时，另有一种猜测指出董卿选择暂别主持舞台的真正原因是她已有孕在身，即将大婚。今年41岁的董卿，在感情生活方面一直众说纷纭。2011年，媒体曾曝出董卿和一男子深夜小酌。董卿的恋情也因此浮出水面。据相关人士介绍该男子名为密春雷，家世显赫。此后，有关董卿的婚讯亦有多次传出。</p><p>\n\t　　而据知情人证实，41岁的董卿将升级做母亲，此次出国深造正是为海外产子：“去美国生完孩子再回来”。</p><div></div><div><ul></ul></div>"}