{"id":10214,"title":"陈建斌前妻吴越照片 爆两人分手内幕","keywords":"陈建,前妻,吴越,照片,两人,分手,内幕,陈建,前妻,吴越,照片,两人,","description":"陈建斌前妻吴越照片 爆两人分手内幕 近日，很多人都在网上说陈建斌前妻是吴越，这让陈建斌吴越两人听了后都觉得好笑，两人并没有结婚怎么吴越就成了陈建斌前妻了.还有人在网上这样搜索陈建斌前妻吴越照片，这搜索词真的让人看到直接就无语了.关于陈建斌吴","content":"<center><img alt=\"陈建斌前妻吴越照片\" src=\"/uploads/3b4bc032df0ca47e605d7ead76f4b1bc.jpg\"></center><p>\n\t　　陈建斌前妻吴越照片 爆两人分手内幕</p><p>\n\t　　近日，很多人都在网上说陈建斌前妻是吴越，这让陈建斌吴越两人听了后都觉得好笑，两人并没有结婚怎么吴越就成了陈建斌前妻了。还有人在网上这样搜索陈建斌前妻吴越照片，这搜索词真的让人看到直接就无语了。关于陈建斌吴越的关系两人之前是恋人，她们俩的关系得从这说起，2000年，吴越与陈建斌从拍《菊花茶》时相识相恋，到后来买房同居，感情一直很好。但是到了电视剧《乔家大院》热播时，陈建斌与蒋勤勤热恋消息传出后，陈建斌吴越分手的消息也被随着爆出了。所以两人根本就没结婚，只是恋爱同居，所以吴越就并不是陈建斌前妻了。</p><p>\n\t　　在曝光陈建斌吴越分手的消息后，就有媒体曾报道过两人分手的过程，是这样的突然有一天，吴越回到家里，发现陈建斌把所有的他的东西都拿走了也没留任何话，两人就这样分手了。随后陈建斌的不辞而别让吴越愤愤不平。在某次吴越在接受媒体采访的时候说：“判断一个人的品德，我是看当一件大事情来临的时候，一刹那，他的反应，他的决定和解决这件事的方法，这能看出一个人的品质。当我看清楚了之后，我心里就会给自己一个答案。”可见当时两人分手的事给吴越带了了很重大的创伤。</p><p>\n\t　　当陈建斌吴越两人分手一年多后，吴越又在次的面对媒体说起了两人的感情：“现在一些媒体一提我，就将我定位成‘陈建斌的前女友’，其实我已经走出来了。我想说的是，我没别人想的那么坚强，也没别人想的那么脆弱。”听到吴越说出这句话时，很多媒体朋友们都开始称其真是个坚强的女孩。</p><div></div><div><ul></ul></div>"}