{"id":10249,"title":"潘粤明演《脱轨时代》 称婚姻出轨双方都有责任","keywords":"潘粤明,脱轨时代,婚姻,出轨,双方,有责任,在演,爱情,轻喜剧,","description":"正在演爱情轻喜剧《脱轨时代》的潘粤明昨日接受沈阳晚报.沈阳网记者电话专访，他称当时演这个角色正对自己的状态，我那时心里很失意，所以看到这个剧本特别有感觉.事后证明我的选择是对的，成片出来后我一看，觉得我当时怎么那么颓废啊！现在真的都很难做","content":"<p>\n\t　　正在演爱情轻喜剧《脱轨时代》的潘粤明昨日接受沈阳晚报、沈阳网记者电话专访，他称当时演这个角色正对自己的状态，“我那时心里很失意，所以看到这个剧本特别有感觉。事后证明我的选择是对的，成片出来后我一看，觉得我当时怎么那么颓废啊！现在真的都很难做到那种状态了，也算是对低潮期的自己一个记录吧。”潘粤明在采访中坦承了他对“出轨”的看法，“不管是因为什么，只要是影响婚姻的事情，作为有家的人是肯定不能做的。”他说，《脱轨时代》是用一种诙谐的方式来阐述一个家庭的爱情矛盾。而出轨其实是一种家庭矛盾的累积，“这事一旦出了，我觉得可能双方都有责任。”</p><p><img alt=\"潘粤明演《脱轨时代》 称婚姻出轨双方都有责任\" src=\"/uploads/e312278308c34630516f21dbb2485757.jpg\"></p><p>\n\t　　带着压抑的心情加入《脱轨时代》，片中潘粤明和另两位主演张静初、吴克羣都有不少对手戏，他的表现可谓相当投入。据悉，片中有一段潘粤明为“前妻”张静初过生日的戏份，潘粤明临场加戏“强吻”张静初，而张静初同样临场反应狠甩他一耳光。“那场戏我拍前都没想到那么演，当然也没和静初商量。结果演得太投入，情绪一上来就收不住了。”他直言，当时拍完他和工作人员都怕张静初真生气了，“结果静初竟然大喊‘太过瘾了！’”不光和“前妻”打，片中潘粤明和“情敌”吴克羣同样大打出手，“那是一场咱俩同时看望静初的戏，由于误会，咱俩就打起来了，场面相当剑拔弩张。其实我们俩心里都有谱，但群众演员紧张了，以为真打了！”</p><div></div><div><ul></ul></div>"}