{"id":10617,"title":"爆囧,脑壳有点昏。。。","keywords":"爆囧","description":"1 闺蜜牙疼，决定把这颗病牙拔了。我陪着捂着腮帮子哼哼唧唧的闺蜜去了附近牙科小诊所。 牙医大哥给闺蜜检查的时候，闺蜜痛的大声啊","content":"<p><strong>1、闺蜜牙疼，决定把这颗病牙拔了。我陪着捂着腮帮子哼哼唧唧的闺蜜去了附近牙科小诊所。<br>\t牙医大哥给闺蜜检查的时候，闺蜜痛的大声啊啊。。。<br>\t大哥擦擦头上的汗，对我说：你出去叫几个街坊邻居过来，你嫂子不在家，我害怕误会。</strong></p><p><strong>2、我对我妈说，我喜欢一个很优秀的男生，但是感觉没有机会。<br>\t我妈说，你怕啥，你虽然差劲，但能有机会接触到这么好的人，说明他命中注定有此一劫。</strong></p><p><strong>3、一大早刚到公司，就看到女主管发飙，不停骂人，摔东西，后来听同事讲，女主管经人介绍相亲，媒人对她说男方家挺有实力，是做铁矿生意的。<br>\t后来才知道，对方家是收废铁的！</strong></p><p><strong>4、打扫卫生翻到老公的私房钱，不好意思给他没收了，把手上的手链褪下来，跟他私房钱放一起。<br>\t跑去跟老公说手链找不到了，让他帮忙找找。没多久，老公拿着手链跟私房钱过来：“老婆，手链找到了，你看看这个钱是不是你一起掉的？”</strong></p><p><strong>5、现在的小偷是越来越善良了，今天在饭店吃饭，付账的时候发现钱包和手机都不见了。。。<br>\t跟老板说明天付，老板告诉我：刚刚有人为你付过了。。。</strong></p><p><strong>6、“学长学姐好，我是临床医学的新生，请问解剖课的尸体是自己带还是学校发？”     <br>\t“自己带不怎么新鲜，学校发的质量又不好，我们一般都是现杀，有关系好的同学也可以互相解剖！”</strong></p><ul></ul><p><strong>7、走着走着下了个蛋，害人不浅</strong></p><p><strong><img alt=\"爆囧,脑壳有点昏。。。\" src=\"/uploads/695e5d098973884038e5cba0dce7f74c.jpg\"></strong></p><div></div><div><ul></ul></div>"}