{"id":10621,"title":"年后的笑段还是这么春节","keywords":"笑段","description":"1 自从年前我结婚之后我妈再也没有对我唠叨过，每天除了看电视剧就是跳广场舞，气色明显比以前好太多了，这就是人们常说的娶了媳妇，旺了娘吧！ 2 过年在家，老妈嫌弃我爹洗衣服不干净，我爹则反过来嫌我妈浪费水。于是降大任于我，我成功集两者之长：既费水","content":"<p><strong>1、自从年前我结婚之后我妈再也没有对我唠叨过，每天除了看电视剧就是跳广场舞，气色明显比以前好太多了，这就是人们常说的“娶了媳妇，旺了娘”吧！</strong></p><p><strong>2、过年在家，老妈嫌弃我爹洗衣服不干净，我爹则反过来嫌我妈浪费水。于是降大任于我，我成功集两者之长：既费水又洗得不干净。</strong></p><p><strong>3、春节过后，老婆问儿子：你是喜欢去奶奶家啊，还是去姥姥家？<br>\t我在旁劝道：他这么点小孩，不要问他这种问题？<br>\t老婆横了我一眼：那你来答？</strong></p><p><strong>4、过年时我听到楼上大姐歇斯底里地大叫：不许叫外卖！你这两天的胃容量是属于妈妈的！养儿千日，用儿吃几天剩菜还不是应该的吗？</strong></p><p><strong>5、今天是春节上班第一天，<br>\t我一早来到自己的座位，<br>\t发现有5张100元的人民币，<br>\t下面还有一张纸条，<br>\t写着：加油！<br>\t落款是领导的名字。<br>\t我感动的掉下了眼泪，<br>\t想不到领导这么有心，<br>\t一上午都很有干劲……<br>\t下午接到领导电话，<br>\t劈头盖脸一顿臭骂，<br>\t问早晨让我去加油，为什么没加？？？</strong></p><p><strong>6、前两天同学聚会，话题天马行空，不知什么时候转到离婚率的问题“谁离婚的举手！”<br>\t有一个男同学犹犹豫豫举手又放下。<br>\t“你什么情况啊？筹划离婚中？？？”<br>\t“你也没说离两次婚的举手啊！”</strong></p><p><strong>7、有猪一样的队友，球技再高也没用</strong></p><p><strong><img alt=\"年后的笑段还是这么春节\" src=\"/uploads/f0c7af67e3677d2ccc2158e6789b4c8d.jpg\"></strong></p><p><strong>8、我说了我不会修水龙头非让我修！</strong></p><p><strong><img alt=\"年后的笑段还是这么春节\" src=\"/uploads/48bd0a76248f66b40d6edc1ff289bcf0.jpg\"></strong></p><p><strong>9、兄弟，不自量力的事不要干，吃了亏没地方说理去</strong></p><p><strong><img alt=\"年后的笑段还是这么春节\" src=\"/uploads/ef6e0374bab1497457a1bb2bc4acd7a8.jpg\"></strong></p><ul></ul><div></div><div><ul></ul></div>"}