{"id":10755,"title":"比较出彩的搞笑逗B","keywords":"搞笑逗B","description":"1 各位刚生孩子的父母，千万不要把小孩的后脑勺睡平，不然以后孩子长大了脱发，如果要留光头，平的不好看。 2 拿着一根牛毛就说自己有一头牛，那叫吹牛；有一头牛展示一头牛，那叫坦然； 有九头牛，把每一头都拉出来溜一遍，那叫炫耀； 有九头牛只露一毛，那","content":"<p><strong>1、各位刚生孩子的父母，千万不要把小孩的后脑勺睡平，不然以后孩子长大了脱发，如果要留光头，平的不好看。</strong></p><p><strong>2、拿着一根牛毛就说自己有一头牛，那叫吹牛；有一头牛展示一头牛，那叫坦然；<br>\t有九头牛，把每一头都拉出来溜一遍，那叫炫耀；<br>\t有九头牛只露一毛，那叫低调；有养牛场却假装不认识牛毛，那叫城府!<br>\t吹牛让人同情，坦然让人亲近，炫耀让人反感，低调让人诚服，城府给人距离！<br>\t我要做个低调的人，所以，我绝对不会告诉你们我家有矿！！！</strong></p><p><strong>3、我羡慕两种女人：一种是特别拽，走路带风，自己干事业贼牛，谁都不屌的那种。<br>\t一种是娇滴滴会撒娇，任谁看见都想拼了老命保护的。<br>\t刚好，我是卡在中间了，既不牛还不会撒娇，一天到晚还死犟死犟！</strong></p><p><strong>4、小时候妈妈给我定过娃娃亲，是个超帅的小哥哥，只是没过几年他们家就搬走了，他当时特别宠我每天都把好吃的零食给我吃，还带我去看他打球，我现在很想他，可是我联系不上他了。<br>\t麻烦笑友们帮我找找，我真的很想跟他再续前缘，虽然过了这么多年，但我依稀记得他好像叫什么彭于晏。</strong></p><p><strong>5、闺蜜小声问我：“你是不是看上刚才给你看病的那个医生了？”<br>\t我惊讶的看着闺蜜说道：“你怎么看出来的！”<br>\t闺蜜淡定的说道：“来的时候，你一直吵吵胃疼！他给你检查的时候，你却说你胸口疼。”<br>\t我。。。</strong></p><ul></ul><p><br><strong>6、女汉子面前，你们都是弱鸡</strong></p><p><strong><img alt=\"比较出彩的搞笑逗B\" src=\"/uploads/b633deeaf7cfaf829a416eec121ef8e3.jpg\"></strong><br><strong>7、连垃圾箱都私奔了，你还好意思说自己单身</strong></p><p><strong><img alt=\"比较出彩的搞笑逗B\" src=\"/uploads/743cd5a8114e76649f136f2ebcd8e14f.jpg\"></strong></p><p><strong>8、小象你确定你在洗澡澡吗</strong></p><p><strong><img alt=\"比较出彩的搞笑逗B\" src=\"/uploads/1a44190a42752b9fb0e027292371b24e.jpg\"></strong><br>\t </p><div></div><div><ul></ul></div>"}