{"id":10850,"title":"生活里的幽默新发现","keywords":"搞笑表演","description":"你的特技表演砸了吧，我咋总感觉你是故意的呢 妹子别拍了，大妈年轻的时候比你好看 妹子，你在看啥，让我看看 你大爷果然还是你大爷，反正我是做不到的 哥们，你是有多猛，骑个单车都能这样 我就欣赏小哥这种精神，请把地址给我 兄弟，我给你个面子，假装没","content":"<p><strong>你的特技表演砸了吧，我咋总感觉你是故意的呢</strong></p><p><strong><img src=\"/uploads/d4b4ba7df126a18186a503a143cd3e03.jpg\"></strong></p><p><strong>妹子别拍了，大妈年轻的时候比你好看</strong></p><p><strong><img src=\"/uploads/29aa4a395c6ecab3adb9e8684da35eab.jpg\"></strong></p><p><strong>妹子，你在看啥，让我看看</strong></p><p><strong><img src=\"/uploads/e6d854c585af64c4d19f1c92f9c36dca.jpg\"></strong></p><p><strong>你大爷果然还是你大爷，反正我是做不到的</strong></p><p><strong><img src=\"/uploads/d50618adf4c5b463e7f63e43f1481414.jpg\"></strong></p><p><strong>哥们，你是有多猛，骑个单车都能这样</strong></p><p><strong><img src=\"/uploads/4928db701a0c7e0604679d235cd19be8.jpg\"></strong></p><p><strong>我就欣赏小哥这种精神，请把地址给我</strong></p><p><strong><img src=\"/uploads/c5f5aa2ced717d22890a385f52f54ca9.jpg\"></strong></p><p><strong>兄弟，我给你个面子，假装没有看到</strong></p><p><strong><img src=\"/uploads/5659076c8ce16ecdaef5c1c288a31cc2.jpg\"></strong></p><p><strong>1、雨天四大怪：下雨必没伞，买伞雨必停，出门伞必丢，带伞必晴天。</strong></p><p><strong>2、有些人耳根子特别软，你说啥好，Ta就买了，你说哪好玩，Ta就去了。你以为人家是没主见吗？错，人家有钱！</strong></p><p><strong>3、那时我还太年轻，不知道这世上的美食，都已经暗中标好了热量。</strong></p><p><strong>4、忘记带手机去上厕所，一切身边的事物都变得有趣了起来。</strong></p><p><strong>5、快消品：指购买后总会很快消失的物品，例如指甲刀、发夹等。</strong></p><p><strong>6、地域拖油瓶：特指数学不及格的黄冈人，不会跳舞唱歌的新疆人，不会骑马射箭的内蒙人、以及没看过升旗的北京人！</strong></p><p><strong>7、跟到好老板你就事业进步，跟到坏老板你就演技进步。</strong></p><p><strong>8、发现总不回你信息的朋友就是那些和你见面时总在玩手机的人。</strong></p><p><strong>9、快乐其实很简单，但你为什么不快乐?因为你连简单的事都做不好。</strong></p><p><strong>10、成年的一大目标就是赚到足够的钱，然后就能像小时候一样无忧无虑地生活。</strong></p><div></div><div><ul></ul></div>"}