{"id":1919,"title":"坑爹！女生趴疾驰出租车顶写作业 的哥老爸被停运","keywords":"实力坑爹","description":"近日，一段女学生坐在出租车车窗上，趴在车顶写作业的视频在网络流传引发关注。经北京时间记者核实，该事件发生在河南省商丘市。商丘市梁园区交通运输管理局工作人员告诉记者，目前将涉事司机停运，后续会联合相关部门做出相应处理。 网友提供的视频显示，一","content":"<div><div><p><strong>近日，一段女学生坐在出租车车窗上，趴在车顶写作业的视频在网络流传引发关注。经北京时间记者核实，该事件发生在河南省商丘市。商丘市梁园区交通运输管理局工作人员告诉记者，目前将涉事司机停运，后续会联合相关部门做出相应处理。</strong></p><p><strong>网友提供的视频显示，一辆豫牌大众出租车在道路行驶。一名身穿白衣的女孩坐在后排右侧的车窗上，半身探出车外趴在车顶似乎正在写作业。看到后车有人拍摄，女孩一脸淡定，没有丝毫惊慌。出租车渐渐驶出拍摄者视线，但女孩依然趴在车顶。</strong></p><p><strong>5月15日，商丘市华达汽车出租租赁公司工作人员在接受北京时间记者采访时表示当时涉事司机正在与车内战友说话，一时疏忽没有注意到女儿趴在车顶。目前已经对该名司机进行了停运处理。</strong></p><p><strong>商丘市梁园区交通运输管理局出租科工作人员告诉记者，该名出租车司机涉及危险驾驶，后期会联合相关部门对其做出相应处罚。<img alt=\"坑爹！女生趴疾驰出租车顶写作业 的哥老爸被停运\" src=\"/uploads/e3063af18c084188630cb8a59a21d609.jpg\"></strong></p></div></div><br><div></div><div><ul></ul></div>"}