{"id":3462,"title":"女子不满三八节没礼物 男友受气挥刀自杀","keywords":"女子,不满,三八节,礼物,男友,受气,挥刀,自杀,近日,义乌,一名,","description":"近日，在义乌一名男子由于在三八妇女节没有送女友礼物，而备受对方的指责，一怒之下挥刀自杀，好在伤的不重，没有生命危险。 三八妇女节，在义乌务工的湖南小伙为女友安排了一顿浪漫的晚餐。但因为没事先准备礼物，小情侣间起了口角。小伙一冲动，拿起水果刀","content":"<p>　　近日，在义乌一名男子由于在三八妇女节没有送女友礼物，而备受对方的指责，一怒之下挥刀自杀，好在伤的不重，没有生命危险。</p><p>　　三八妇女节，在义乌务工的湖南小伙为女友安排了一顿浪漫的晚餐。但因为没事先准备礼物，小情侣间起了口角。小伙一冲动，拿起水果刀刺进自己的腹部……</p><p>　　小马和小童是湖南老乡，两人都是21岁。一年前，两人在义乌相识、相恋，现在一起租住在稠江街道。</p><p>　　3月8日，周围很多女性朋友都收到了节日礼物，这让小童很是羡慕。</p><p>　　小马也不是不浪漫，为了给女友庆祝节日，他选了一家挺气派的餐馆请小童吃晚餐，享受二人世界。</p><p>　　两人找了一个靠窗的位置坐下。等待服务员上菜时，小童不经意地说道：“你看街上，人家都拿着花、礼物送给女朋友，你怎么就没准备点礼物给我呢？”</p><p>　　一开始，小马也不生气，他开玩笑地回应说：“你又不是妇女，为什么要送礼物啊！再说今天买礼物多浪费钱。”</p><p>　　听男友这么一说，小童就不开心了，觉得小马对自己太抠，不爱自己，连节日礼物都不舍得买，她开始数落起小马来。</p><p>　　就这样，两人在饭桌上互不相让，你一句我一句，最后大声争吵起来。结果，这顿浪漫的三八节晚餐也没吃成，两人就气冲冲地回家了。</p><p>　　回到家后，小马就躲进房间看电视。一看男友毫无悔改之意，不上来哄哄自己，小童更加生气，冲进房间对着小马又是一顿数落。</p><p>　　小马的脾气上来也不太好控制，看着女友这样数落自己，他也狠狠地骂了回去。</p><p>　　两人越骂越凶，小马一冲动，随手拿起边上一把水果刀，直直地刺进了自己的左侧腹部，吼着“我死了，你就开心了”！</p><p>　　小童惊呆了，直到小马因出血疼痛瘫坐在地上，她才想到拨打120急救中心电话。</p><p>　　小马被送往復元医院。经过急诊外科医生的检查，发现小马的伤口有3厘米左右长，深达四五厘米，还好没有伤及腹腔，“如果再刺深一点，后果就不堪设想了。”</p><p>　　在医院里，小童悉心地照顾着小马，两人已经完全看不出争吵过的痕迹。</p><p>　　好在小马恢复良好，今天就可以出院了。出院前，小情侣不好意思地说：“再也不这么冲动了！”</p><div></div><div><ul></ul></div>"}