{"id":3731,"title":"女子自称清朝公主 成功诈骗上百万","keywords":"女子,自称,清朝,公主,成功,诈骗,百万,近日,陕西,警方,破获,一起,","description":"近日，陕西警方破获了一起女子自称清朝公主行骗的事件，据悉河南女子王某以清朝三公主的身份伙同其他人，先后在多省进行诈骗，先后非法获得资金572万余元，最后被警方抓获. 2014年7月27日，青年路派出所接到一个13岁女孩报警，称自己的养母王某离家24小时未","content":"<p>\n\t　　近日，陕西警方破获了一起女子自称清朝公主行骗的事件，据悉河南女子王某以清朝三公主的身份伙同其他人，先后在多省进行诈骗，先后非法获得资金572万余元，最后被警方抓获。</p><p><img alt=\"女子自称清朝公主\" src=\"/uploads/617a079694c0b1b13ee6d15a68be468a.jpg\"></p><p>\n\t　　2014年7月27日，青年路派出所接到一个13岁女孩报警，称自己的养母王某离家24小时未归，疑被人控制在西北二路的一间办公室内。</p><p>\n\t　　派出所民警迅速出警，很快将王某（女）及其同事杨某解救出来，并抓获涉嫌非法拘禁的嫌疑人6人。然而，涉嫌非法拘禁的嫌疑人王某（男，69岁）却当场报警，称自己被骗了。</p><p>\n\t　　王某（男）称，王某（女）和杨某曾以解冻民国时期民族资产为由，分多次骗走自己共计317万元。意识到自己被骗，王某（男）多次要钱无果，这才将二人控制起来。</p><p>\n\t　　初步了解案情后，西安市公安莲湖分局确定这是一起特大诈骗案，刑侦大队和青年路派出所随即成立联合专案组，全力展开案件侦破工作。</p><p>\n\t　　专案组分为三个行动组。一是调查走访组，对王某（男）及其社会关系进行详细询问，了解其被骗经过；二是勘验搜查组，对王某（女）位于西北二路的办公室进行全面搜查；三是审查讯问组，落实诈骗金额、去向和其他嫌疑人情况。</p><p>\n\t　　通过多渠道细致调查，案情逐渐浮出水面。原来，王某（女，48岁，河南卢氏县人）、杨某（西安市碑林区人）伙同姜某、易某、杨某（湖北永安县人）、于某、黄某等7人，于2013年年初成立公司，由王某伪装清朝皇室后裔身份，伪造中央军委证件，在贵州、河南、四川等省份，购买大量的假美金、假金条充当解冻的民族资产，并对外宣称解冻的民族资产回收后国家将给予三倍的高额奖励。团伙成员相互配合骗取受害人信任，以解冻更多民族资产为由，先后作案10余起，诈骗6人共计572万元。</p><p>\n\t　　据了解，王某对外自称爱新觉罗氏三公主，称金库中有巨额民族资产通过正常途径无法解冻，如需解冻，需要一大笔运费、疏通关系费等，而这些民族资产一旦解冻，回收后国家将给与三倍的高额奖励。“他们告诉受害人，如果拿出一笔赞助费，等这些民族资产解冻后，将按赞助的比例来分钱。”办案民警说。</p><p>\n\t　　办案民警介绍，该团伙成立公司时，曾在某四星级酒店中举办过庆祝大会，以赠送礼品、免费吃饭为诱饵，吸引了近500人参会，而这其中，大部分都是60岁到80岁的老年人。</p><div></div><div><ul></ul></div>"}