{"id":3936,"title":"公务员五年增长57% 录用公务员的人数逐年增多","keywords":"公务员,五年,增长,57%,录用,人数,逐年,增多,近年来,","description":"近年来，在公务员普遍抱怨工资较低要求加薪的同时，近日根据人社部公布的影响报告显示公务员的录取人数从2009年到现在工资增长了近57%. 昨日，人力和社会保障部发布的《2013年度人力资源和社会保障事业发展统计公报》透露，2013年，全国共录用公务员20.4万","content":"<p>\n\t　　近年来，在公务员普遍抱怨工资较低要求加薪的同时，近日根据人社部公布的影响报告显示公务员的录取人数从2009年到现在工资增长了近57%。</p><p><img alt=\"公务员五年增长57%\" src=\"/uploads/07995db6b39bcf447fe88aeca5b02601.jpg\"></p><p>\n\t　　昨日，人力和社会保障部发布的《2013年度人力资源和社会保障事业发展统计公报》透露，2013年，全国共录用公务员20.4万人。相比起2009年的13万余人，增幅达57%。</p><p>\n\t　　据人社部历年公布的公报，2009年、2010年、2011年、2012年，全国共录用公务员人数分别为13万余人、18万余人、19万余人、18.8万人。相比4年前，2013年录用公务员人数比2009年增加了7万人左右，增幅超过50%。　　据国家公务员局网站去年6月发布的消息，2008年度、2009年度、2010年、2011年和2012年全国公务员总数分别是659.7万人、678.9万人、689.4万人、702.1万人和708.9万人。2012年底全国公务员总数比4年前的2008年增加了49.2万人，增幅7.5%。</p><p>\n\t　　2013年公报指出，事业单位聘用制度推行率、事业单位工作人员合同签订率均超过了90%。全国事业单位岗位设置基本实现制度入轨，全国事业单位岗位设置完成率超过90%。事业单位公开招聘制度推行率达到了90%。事业单位新进人员公开招聘工作已经在全国范围内基本实现全覆盖，初步建立了民主、公开、竞争、择优选拔新进人员的制度框架。</p><p>\n\t　　2013年安置军队转业干部4万余名。安置到党政机关和参公事业单位的占计划分配军队转业干部总数的82.7%，事业单位的占15.7%，国有企业的占1.6%；1.2万余名师团职干部得到重点安置，3000余名功臣模范以及长期在艰苦边远地区和特殊岗位工作的军转干部得到照顾安置。</p><div></div><div><ul></ul></div>"}