{"id":395,"title":"国家林业和草原局：保护候鸟出大招！加强秋冬季候鸟保护","keywords":"国家林业","description":"国家林业和草原局发布，秋冬季是候鸟大规模迁徙和集群活动的季节，也是乱捕滥猎 滥食鸟类等野生动物非法案件的高发期。少数不法分子在候鸟迁徙路线沿途大肆捕捉 毒杀 非法催肥饲养和贩运候鸟，特别是近期河北 辽宁等地又相继出现破坏鸟类资源案件，造成了恶","content":"<p><strong>国家林业和草原局发布，秋冬季是候鸟大规模迁徙和集群活动的季节，也是乱捕滥猎、滥食鸟类等野生动物非法案件的高发期。少数不法分子在候鸟迁徙路线沿途大肆捕捉、毒杀、非法催肥饲养和贩运候鸟，特别是近期河北、辽宁等地又相继出现破坏鸟类资源案件，造成了恶劣的社会影响。为切实巩固生态文明建设成果，坚决遏制并严厉打击伤害候鸟等野生动物违法犯罪活动，确保候鸟的迁徙及越冬安全，现将有关事项通知如下：</strong></p><p><strong>一、强化组织协调，层层压实责任</strong></p><p><strong>各地要主动作为，积极履行野生动物主管部门的职责，建立健全野生动物保护领导责任制，推动将鸟类等野生动物保护纳入地方各级领导绩效考核内容。没有建立打击野生动物非法贸易联席会议制度的，要抓紧建立，联合制定行动方案，联合开展保护候鸟执法。要主动配合地方政府建立候鸟迁飞安全责任制度，在重点区域和重点时段集中力量有针对性地开展专项打击行动，严防非法猎杀候鸟等重大事件的发生，确保候鸟在本辖区内迁徙及越冬安全。</strong></p><p><strong>二、落实保护措施，严格执法监管</strong></p><p><strong>各地要准确掌握本辖区候鸟种群及栖息地保护现状，配合地方政府组织力量在野生动物主要分布地和集群活动区开展巡护、值守、清网、清套、清夹和清除毒饵等专项行动，彻底铲除威胁候鸟安全隐患，并配合有关部门进行问题追查；要加强与公安、市场监管、海关、边防、交通运输等部门的沟通与协调，联合对辖区内野生动物人工饲养繁育和经营利用场所、非法生产和销售鸟网情况、野生动物及其产品运输情况以及电子商务、快递物流和社交媒体等涉及猎捕、买卖野生动物及其产品的情况逐一进行检查，发现有非法饲养和非法储存、运输、递送和买卖野生候鸟及产品的，以及销售非法猎捕工具的，要严格依法查处；要切实做好候鸟禽流感等野生动物疫源疫病监测防控工作，加密监测巡查路线，消除监测盲区；要进一步落实监测岗位职责，做好信息报送和节假日应急值守，密切关注并及时报告候鸟等野生动物的异常情况，严防疫情扩散蔓延。</strong></p><p><strong>三、认真监督检查，务求取得实效</strong></p><p><strong>各地要围绕国家林业和草原局关于加强秋冬季候鸟保护执法、打击非法犯罪活动的工作部署和要求，切实落实好辖区内候鸟等野生动物保护措施，汇总梳理情况，分析成因，提出解决措施和建议，形成总结报告。国家林业和草原局各派出机构要切实履行好监督职能，及时了解情况、到场检查、提出解决方案，形成督导报告。要邀请纪检、监察、检察机关共同对打击乱捕滥猎及非法交易野生动物的情况进行监督检查。国家林业和草原局将对重大伤害候鸟等野生动物的案件进行约谈和通报，对因保护监管不到位导致发生上述违法犯罪大案和要案的地区，要依法依规追究责任。</strong></p><div></div><div><ul></ul></div>"}