{"id":4127,"title":"pm2.5确认为致癌物 首次指认大气污染对人类致癌","keywords":"pm2.5,认为,致癌物,首次,指认,大气污染,人类,致癌,","description":"上个月国际癌症研究机构（IARC）在里昂的会上，已经把大气污染确认定为致癌物，这也得到了专家的公认.其实具体细地讲就是大气颗粒物，也就是所谓的PM2.5是一种确认的人类致癌物！ PM2.5颗粒可以进入肺泡，并在此沉积，导致肺部疾","content":"<p>\n\t　　上个月国际癌症研究机构（IARC）在里昂的会上，已经把大气污染确认定为致癌物，这也得到了专家的公认。其实具体细地讲就是大气颗粒物，也就是所谓的PM2.5是一种确认的人类致癌物！</p><p>\n\t　　PM2.5颗粒可以进入肺泡，并在此沉积，导致肺部疾病。许多研究证明，PM2.5浓度增加与附近医院急诊和门诊患者增加显著相关。在稳定的环境下，若要PM2.5从空气中沉降下来，至少需要15年。而世界卫生组织下属国际癌症研究机构于2013年10月发布报告，首次指认大气污染“对人类致癌”，并视其为普遍和主要的环境致癌物，其重要组成部分可吸入颗粒物可被认定为一类致癌物，危险程度与烟草同级。</p><div></div><div><ul></ul></div>"}