{"id":4195,"title":"香港女子自导自演“女婴失踪案”被拘","keywords":"香港,女子,自导,自演,女婴失踪案,被拘,11月,23日,现","description":"11月23日，现年31岁的吴某报警称其6个月大的女儿俞凯晴失踪，并称在途经九龙城贾炳达道及南角道交界时，遭遇一名操内地口音的女子问路后，婴儿车上的女婴就不知所终，警方接报后在该地段搜查多日仍然毫无收获. 失踪女婴名俞凯晴，约六个月大，其31岁的母亲","content":"<p>\n\t　　11月23日，现年31岁的吴某报警称其6个月大的女儿俞凯晴失踪，并称在途经九龙城贾炳达道及南角道交界时，遭遇一名操内地口音的女子问路后，婴儿车上的女婴就不知所终，警方接报后在该地段搜查多日仍然毫无收获。</p><p>\n\t　　失踪女婴名俞凯晴，约六个月大，其31岁的母亲吴某与已婚男友俞某相恋，并于半年前生下小凯晴。</p><p>\n\t　　与此同时，香港也掀起了一场全城寻婴的狂潮，当地不少香港父母更是一度陷入拐卖婴儿的恐惧中。虽然香港保安局局长黎栋国日前曾表示，过去十年共有7宗涉嫌拐婴案，且全不涉及內地人，此案涉及内地婴儿拐卖团伙的可能性极微，但仍无法消除众多父母的疑虑。</p><p>\n\t　　据悉，由于吴某在报案时表现得极度冷静，且无人可以证实案发当日女婴就在婴儿车内，警方担心案件另有内情，便集中在吴某家中搜证，还翻看了11月23日其住所监控录像，发现由于被婴儿车顶篷遮挡，无法判断女婴是否就在车内；警方甚至曾将放在凯晴居住的新蒲岗大厦外72袋垃圾，搬上天台搜索，但仍未有任何发现。</p><p>\n\t　　谁知案件在12月2日峰回路转，痛失爱女的母亲原来早已将死因不明的女儿抛弃。早前，吴某也曾表示不在乎警方怀疑她，更在网络上扬言，要悬赏50万港元寻找爱女。然而，面对警方连日盘问调查，吴某终于承认女儿并未失踪，早于11月17日就已在家中死亡，尸体也早已被抛弃至垃圾桶。</p><p>\n\t　　有港媒消息称，吴某于11月17日上午发现女儿对外界没有任何反应，认为女婴已经窒息死亡，大惊之下将女婴遗体放入一个小提琴盒内，假装成垃圾扔进了垃圾桶，并在事后故布疑阵，谎称女儿被人偷走。</p><p>\n\t　　吴某因涉嫌非法处理尸体，已被通宵扣查。</p><div></div><div><ul></ul></div>"}