{"id":4475,"title":"最新量子通信芯片仅为现有装置的1/1000","keywords":"通信芯片","description":"新加坡研究人员在最新一期《自然光子学》杂志上撰文称，他们开发出一种量子通信芯片，尽管其块头仅为现有装置的千分之一，但能提供同样出众的量子安全技术，可用于智能手机 平板电脑和智能手表等紧凑型设备内，提升其通信安全性。 据美国物理学家组织网近日","content":"<p><strong>新加坡研究人员在最新一期《自然·光子学》杂志上撰文称，他们开发出一种量子通信芯片，尽管其“块头”仅为现有装置的千分之一，但能提供同样出众的量子安全技术，可用于智能手机、平板电脑和智能手表等紧凑型设备内，提升其通信安全性。</strong></p><p><strong>据美国物理学家组织网近日报道，由南洋理工大学刘爱群（音译）教授领导的团队最新开发的微型芯片大小约3毫米，使用量子通信算法提供增强的安全性——将密码集成在被传递信息中形成安全的量子密钥，信息收到后，会与密钥一起销毁，从而使其成为一种极其安全的通信形式。</strong></p><p><strong>研究人员表示，最新量子芯片需要的空间仅为目前量子通信设备的千分之一，这为更安全的通信技术打开了大门，可安装在智能手机、平板电脑和智能手表等紧凑型设备内。此外，它还为用于在线交易和电子通信的更好的加密方法奠定了基础。</strong></p><p><strong>随着互联网服务的激增，诸如WhatsApp、Facebook、Snapchat等电子邮件和消息传递平台已经创建了自己的安全通信渠道——所谓的“经典通道”。相比之下，携带信息的量子信道具有集成到加密数据中的安全协议。每个通道彼此不同，从而减少甚至消除了在传输过程中信息被拦截或泄漏的风险。</strong></p><p><strong>研究人员称，量子技术不需要“经典信道”中必需的密码或生物特征数据的额外传输，这消除了拦截或信息泄漏的风险，从而创建出几乎不可破坏的加密。</strong></p><p><strong>此外，新量子通信芯片将具有成本效益，因为它使用标准的工业材料硅等制成，易于制造。</strong></p><p><strong>刘爱群说：“量子技术是安全通信的未来，这项研究使我们距离量子计算和通信更近，有助于开发下一代通信设备，并提高诸如银行在线金融门户等数字服务。”</strong></p><p><strong>该团队目前正致力于开发传统光通信系统和量子通信系统的混合网络，这将改善量子技术的兼容性，使其可用于更广泛的应用程序，如互联网连接等。</strong></p><div></div><div><ul></ul></div>"}