{"id":5032,"title":"赏雪别忘护眼","keywords":"赏雪,护眼","description":"今年，似乎除了北京，全国大部分区域的人们都欣赏了雪花漫天飞舞的美景，但在雪地里玩得时间长了，有些人会出现眼睛痛 怕光 流泪，不能睁眼等症状。这很可能是雪盲症的表现。 雪盲症主要是紫外线对眼表损伤所引起的炎症。因为干净新鲜的雪面反射率高达95%，","content":"<p><strong><img src=\"/uploads/55dbe04b2810e1b0fd1c15e8a5f468db.jpg\"></strong></p><p><strong>今年，似乎除了北京，全国大部分区域的人们都欣赏了雪花漫天飞舞的美景，但在雪地里玩得时间长了，有些人会出现眼睛痛、怕光、流泪，不能睁眼等症状。这很可能是雪盲症的表现。</strong></p><p><strong>雪盲症主要是紫外线对眼表损伤所引起的炎症。因为干净新鲜的雪面反射率高达95%，太阳光照射到雪面，紫外线通过雪面的散射对人的眼睛形成持续刺激，人眼在长时间的光照刺激下，眼角膜和结膜的上皮细胞就会受到损害，发生上皮脱落、红肿等炎症反应，混浊的角膜，也会影响视力。</strong></p><p><strong>雪盲症一般发生在雪后天晴、气温较低的白天，但有时即便是阴天，不戴墨镜在积雪地上活动久了，也有可能出现雪盲症状。因为云雾并不能完全阻隔紫外线。</strong></p><p><strong>由于每个人体质存在差异，所以症状缓解时间并不相同。但如果结膜充血严重，畏光、流泪持续不缓解的时候，必须第一时间去看医生，而不是凭感觉自我判断。</strong></p><p><strong>“比如，有些糖尿病患者角膜知觉是减退的，所以角膜的感觉不敏感，如果完全凭自己的经验就会耽误病情。”北京大学人民医院眼科主治医师张钦说。</strong></p><p><strong>目前，临床上针对雪盲症的治疗主要是支持治疗，以减轻疼痛等症状、预防角结膜感染为主。如果出现了雪盲症，并且没有相应的眼药水，第一时间应该进行冷敷。用冷毛巾敷眼，可以促进血管收缩，减少炎症反应，同时可以降低神经敏感性，还能起到镇痛的作用。其次，在医生的指导下可以涂用眼膏，起到隔离、保护作用。如果出现眼红、眼痛、眼磨、烧灼感、畏光、流泪、视物模糊等症状，可在医生指导下用一些抗生素类的眼药水或眼药膏进行治疗。</strong></p><div></div><div><ul></ul></div>"}