{"id":5375,"title":"美堪萨斯州超级雷暴形成巨大的上升气流 景象壮观似世界末日","keywords":"堪萨斯,超级,雷暴,形成,大的,上升,气流,景象,壮观,世界,末日,","description":"超级雷暴 美国超级雷暴 美国当地时间2014年5月10日，堪萨斯州，超级雷暴形成巨大的上升气流，景象壮观似世界末日，令人惊叹.","content":"<p><img alt=\"美堪萨斯州超级雷暴形成巨大的上升气流 景象壮观似世界末日\" src=\"/uploads/5873562cf484a07ca74468fc36fc9286.jpg\"></p><p>\n\t超级雷暴</p><p><img alt=\"美堪萨斯州超级雷暴形成巨大的上升气流 景象壮观似世界末日\" src=\"/uploads/c17ce34f8131bf07fd138703591028c2.jpg\"></p><p>\n\t美国超级雷暴</p><p>\n\t 美国当地时间2014年5月10日，堪萨斯州，超级雷暴形成巨大的上升气流，景象壮观似世界末日，令人惊叹。</p><div></div><div><ul></ul></div>"}