{"id":581,"title":"5月1日起这些人民币停止流通！抓紧去银行兑换","keywords":"人民币","description":"一毛钱 两毛钱的小面额人民币 越来越少见了 现在你家里还有这种硬币吗 ▼ 打开APP，查看更多精彩图片 有这些硬币和纸币 赶紧去银行兑换吧 这些人民币停止流通 2019年4月30日停止兑换 根据《中国人民银行公告［2018］第6号》文件，2018年5月1日起停止第四套人","content":"<p><strong>一毛钱、两毛钱的小面额人民币</strong></p><p><strong>越来越少见了</strong></p><p><strong>现在你家里还有这种硬币吗</strong></p><p><strong>▼</strong></p><p><strong><img alt=\"t0107cc697ee5e6bea3.jpg?size=580x352\" src=\"/uploads/45eb2ec72fa84a43fed4a6ae60d0de2c.jpg\"></strong></p><div><strong>打开APP，查看更多精彩图片</strong></div><p>\t </p><p><strong>有这些硬币和纸币</strong></p><p><strong>赶紧去银行兑换吧</strong></p><p><strong>这些人民币停止流通</strong></p><p><strong>2019年4月30日停止兑换</strong></p><p><strong>根据《中国人民银行公告［2018］第6号》文件，2018年5月1日起停止第四套人民币100元、50元、10元、5元、2元、1元、2角纸币和1角硬币在市场上流通。</strong></p><p><strong>温馨提示，第四套人民币部分券别的集中兑换期为2018年5月1日至2019年4月30日。在此期间，其持有者可到各银行业金融机构营业网点办理兑换。</strong></p><p><strong>如图▼</strong></p><p><strong><img alt=\"t0101ad93170ec37fa8.jpg?size=674x1144\" src=\"/uploads/7822bcf729fd5b8de169d9b6b6401e77.jpg\"></strong></p><p><strong><img alt=\"t016ccc4429d24c8ed7.jpg?size=660x1152\" src=\"/uploads/8307154201b31e36c4b36d18d3e7f7c4.jpg\"></strong></p><p><strong><img alt=\"t010371189d9a95c5fa.jpg?size=648x598\" src=\"/uploads/961dcf5275a4443e196805151a9c93ff.jpg\"></strong></p><p><strong><img alt=\"t01417f5a125cc0de44.jpg?size=610x570\" src=\"/uploads/e8a65de4a188ac7ea5d216b45e475442.jpg\"></strong></p><p><strong><img alt=\"t01c7f34d80faf6aa76.jpg?size=608x1128\" src=\"/uploads/ee4674084ea92a5786cb5db2b18aa70c.jpg\"></strong></p><p><strong><img alt=\"t01ba1d79376abd996c.jpg?size=646x1128\" src=\"/uploads/d3612e55f5ac06f63c02a777a422f2a2.jpg\"></strong></p><p><strong><img alt=\"t01699f1fd9f7636ad5.jpg?size=602x554\" src=\"/uploads/0689290f00e5f1b0574a75367e157095.jpg\"></strong></p><p><strong><img alt=\"t016d835e47af286da4.jpg?size=606x282\" src=\"/uploads/6d647a607907ebe306b8e889bff324e4.jpg\"></strong></p><p><strong>本次流通公告中，未提及第四套人民币中的一角纸币和五角纸币。</strong></p><p><strong>流通过的菊花一角硬币收藏价值不大</strong></p><p><strong>菊花一角硬币退市后，很多人便开始有意收藏。不过，并不是所有的菊花一角都有收藏价值。</strong></p><p><strong>据介绍，收藏流通使用过的人民币价值不大，除非特别稀有的。菊花一角硬币在1991年至2000年发行，2000年没有发行流通币，所以市面上见到的大多都是1991年至1999年，第一年和最后一年的具有一定收藏价值，如果遇到可以留着。2000年的目前市面上几乎没有，收藏价值自然更高。</strong></p><p><strong>兰花一角硬币和一角纸币还能使用吗</strong></p><p><strong>那么，普通市民手里的兰花一毛钱该怎么办？还能花出去吗？</strong></p><p><strong>据银行工作人员介绍，目前，兰花一角硬币和一角纸币均正常流通，退出流通市场的只有第四套人民币中的菊花一角硬币。</strong></p><p><strong><img alt=\"t019ba89ca8ec119c71.jpg?size=1032x774\" src=\"/uploads/b09deca7a065965732a83d594855c03d.jpg\"></strong></p><p><strong>▲兰花一角硬币和一角纸币目前流通正常</strong></p><p><strong>对于部分商户拒收一角纸币的行为，央行曾明确表示拒收现金涉嫌违法违规。人民币是我国的法定货币，不管是多大的面值，都可以正常流通。当然，如果市民觉得大量的小钱不方便使用，可以到银行兑换。</strong></p><div></div><div><ul></ul></div>"}