{"id":5811,"title":"徐峥谈中国女排比赛令人想哭：她是一种生命力","keywords":"生命力","description":"徐峥在微博上为中国女排再胜利喝彩，也谈了自己的感受：为什么在看中国女排比赛的时候老是会让人想哭呢？我想中国女排有一种超级的能量，这种能量不仅仅是体育，也不仅仅是胜利，她是一种生命力！她会感染你，让你在感受到喜悦，振奋，坚毅的同时。还能体会","content":"<p><strong>徐峥在微博上为中国女排再胜利喝彩，也谈了自己的感受：“为什么在看中国女排比赛的时候老是会让人想哭呢？我想中国女排有一种超级的能量，这种能量不仅仅是体育，也不仅仅是胜利，她是一种生命力！她会感染你，让你在感受到喜悦，振奋，坚毅的同时。还能体会到一种隐忍的，令人肝肠寸断的情感。这真的是一种大美啊！”</strong></p><p><strong><img src=\"/uploads/203b51fd40ff8f37e8895c1e0b99d0ff.jpg\"></strong></p><p><strong>据悉，徐峥执导了电影《我和我的祖国》中的《夺冠》单元，其内容正是84年中国女排击败美国女排的光辉时刻。</strong></p><p><strong><img alt=\"徐峥\" src=\"/uploads/43a1e5f843065a0043da281a27474b80.jpg\"></strong></p><p><strong>徐峥</strong></p><p><strong>网友们也纷纷表示：“有一种精神叫中国女排精神！”“认同，佩服这群姑娘们！热血，燃！”</strong></p><div></div><div><ul></ul></div>"}