{"id":6862,"title":"柳岩泰国水乡拍MV 再展胸器魅力","keywords":"柳岩,泰国,水乡,再展,胸器,魅力,近日,网友,称为,大胆,柳岩,远赴,","description":"近日，被网友称为柳大胆的柳岩远赴泰国水乡为《情路透春光》拍摄MV，再展性感露酥胸. 近日，柳岩在泰国曼谷拍摄《情路透春光》MV现场照首次曝光.只见她以一袭纯白裹胸裙出镜，酥胸微露，性感非常.据悉，拍摄时值泰国最炎热的盛夏，室外温度直逼43摄氏度，","content":"  近日，被网友称为“柳大胆”的柳岩远赴泰国水乡为《情路透春光》拍摄MV，再展性感露酥胸。\t\t\t\t\t\n\t\t\t\t\n\t\t\t\t\n\t\t\t\t<center><img src=\"/uploads/allimg/201412/20141219112316195.jpg\" alt=\"柳岩泰国水乡拍MV 再展胸器魅力\"></center>\n\t\t\t\t\n\t\t\t\t近日，柳岩在泰国曼谷拍摄《情路透春光》MV现场照首次曝光。只见她以一袭纯白裹胸裙出镜，酥胸微露，性感非常。据悉，拍摄时值泰国最炎热的盛夏，室外温度直逼43摄氏度，从清早就开始拍摄的柳岩在摄像机前不顾闷热的天气，始终保持甜美笑容，而每到拍摄间隙就豪爽的端起冰水狂灌用来降温保证拍摄状态。图为柳岩顶酷暑不惧蚊虫敬业拍摄。\t\n\t\t\t\t\n\t\n\t\n\n<div></div><div><ul><li><span>1</span></li><li><b>2</b></li><li><b>3</b></li><li><b>4</b></li><li><b>5</b></li><li><b>下一页</b></li></ul></div>"}