{"id":6927,"title":"仁川亚运会开幕式 鸟叔卖力献唱","keywords":"仁川,亚运会,开幕式,鸟叔,卖力,献唱,近日,韩国,仁川,亚运,会的,","description":"近日，在韩国仁川亚运会的开幕式上，曾经红遍全球的鸟叔与众明星一道为大家卖力演唱，吸引了很多人的关注. 2014年9月19日，仁川亚运会开幕式，EXO组合现场献唱.近日，在韩国仁川亚运会的开幕式上，曾经红遍全球的鸟叔与众明星一道为大家卖力演唱，吸引了","content":"  近日，在韩国仁川亚运会的开幕式上，曾经红遍全球的鸟叔与众明星一道为大家卖力演唱，吸引了很多人的关注。\t\t\t\t\t\n\t\t\t\t\n\t\t\t\t\n\t\t\t\t<center><img src=\"/uploads/allimg/201412/20141219112046935.jpg\" alt=\"仁川亚运会开幕式 鸟叔卖力献唱\"></center>\n\t\t\t\t\n\t\t\t\t2014年9月19日，仁川亚运会开幕式，EXO组合现场献唱。\t\n\t\t\t\t\n\t\n\t\n\n<div></div><div><ul><li><span>1</span></li><li><b>2</b></li><li><b>3</b></li><li><b>4</b></li><li><b>5</b></li><li><b>6</b></li><li><b>下一页</b></li></ul></div>"}