{"id":7001,"title":"央视女主播穿肉色内衣主持 引遐想","keywords":"央视,主播,肉色,内衣,主持,遐想,近日,央视,体育频道,主持人,","description":"近日，央视体育频道女主持人朱晓琳以穿肉色衣服主持节目，一下吸引了很多人的关注，让央视主持人着装正规的印象得到了改善. 央视女主播穿肉色内衣主持近日，央视体育频道女主持人朱晓琳以穿肉色衣服主持节目，一下吸引了很多人的关注，让央视主持人着装正","content":"  近日，央视体育频道女主持人朱晓琳以穿肉色衣服主持节目，一下吸引了很多人的关注，让央视主持人着装正规的印象得到了改善。\t\t\t\t\t\n\t\t\t\t\n\t\t\t\t\n\t\t\t\t<center><img src=\"/uploads/allimg/201412/20141219111739185.jpg\" alt=\"央视女主播穿肉色内衣主持 引遐想\"></center>\n\t\t\t\t\n\t\t\t\t央视女主播穿肉色内衣主持\t\n\t\t\t\t\n\t\n\t\n\n<div></div><div><ul><li><span>1</span></li><li><b>2</b></li><li><b>3</b></li><li><b>4</b></li><li><b>5</b></li><li><b>下一页</b></li></ul></div>"}