{"id":8077,"title":"《蝴蝶公墓》曝人物海报 造“高概念”蝶恋悬奇","keywords":"蝴蝶公墓","description":"蝴蝶公墓 海报 蝴蝶公墓 海报 最会拍爱情导演执导悬疑IP，不一样的画风将碰撞出怎样别具一格的作品？由张俪 锦荣 李子峰 李若彤等主演的奇幻爱情巨制《蝴蝶公墓》继宣布将于10月20日破茧大银幕后，人物海报于今日再度重磅曝光。海报中，八位主演正式亮相，蝶","content":"<p><strong><img alt=\"蝴蝶公墓 海报\" src=\"/uploads/allimg/170914/2013521264-0.jpg\" title=\"蝴蝶公墓 海报\"></strong></p><p><strong>蝴蝶公墓 海报</strong></p><p><strong><img alt=\"蝴蝶公墓 海报\" src=\"/uploads/allimg/170914/2013525c7-1.jpg\" title=\"蝴蝶公墓 海报\"></strong></p><p><strong>蝴蝶公墓 海报<br>\t“最会拍爱情”导演执导“悬疑”IP，不一样的画风将碰撞出怎样别具一格的作品？由张俪、锦荣、李子峰、李若彤等主演的奇幻爱情巨制《蝴蝶公墓》继宣布将于10月20日破茧大银幕后，人物海报于今日再度重磅曝光。海报中，八位主演正式亮相，蝶变光影若影若现；男女主演张俪、锦荣更半裸出镜，性感身材仍引发观众无限遐想。据悉，此次《蝴蝶公墓》被搬上大银幕，将结合奇幻、爱情两大经典元素，以颇具颠覆性的方式为观众呈现一场奇情动魄的蝶恋悬奇。</strong></p><p><strong>《蝴蝶公墓》原著作者蔡骏被誉为“中国悬疑小说第一人”，作为蔡骏的经典代表作，由于文字沉郁优美，情节丝丝入扣，广受网友追捧。今年恰逢小说出版十年，《蝴蝶公墓》此时登上大屏幕，引大批“原著粉”强烈关注。据悉，电影版《蝴蝶公墓》将会是原著小说的番外篇，主要讲述尚小蝶成长后的故事，主角的命运，爱情的主题，奇幻的旅程，都将是原著的延续与颠覆。<br>\t影片主要讲述的是，身材畸形的尚小蝶因误入蝴蝶公墓而变身美女，因此得知自己是半蝶人的身世之谜。于是，酝酿了近一个世纪的半蝶人族群拯救阴谋，即将在她身上展开。</strong></p><div></div><div><ul></ul></div>"}