{"id":8334,"title":"《黄金时代》艺术剧照 冯绍峰汤唯造型曝光","keywords":"黄金时代,艺术,剧照,冯绍峰,汤唯,造型,曝光,近日,冯绍峰,汤唯,","description":"近日，由冯绍峰与汤唯主演的电影《黄金时代》曝光了一组剧照，片中的两人感情深厚，但也时而发生冲突，演技逼真，引人关注. 近日，由冯绍峰与汤唯主演的电影《黄金时代》曝光了一组剧照，片中的两人感情深厚，但也时而发生冲突，演技逼真，引人关注.","content":"<center><img src=\"/uploads/cca783bc88b1887ce94e959087c94a76.jpg\"></center>\n\t\t\t\t\n\t\t\t\t\t\t\t\t\n\t\n\t近日，由冯绍峰与汤唯主演的电影《黄金时代》曝光了一组剧照，片中的两人感情深厚，但也时而发生冲突，演技逼真，引人关注。\n\n<div></div><div><ul><li><span>1</span></li><li><b>2</b></li><li><b>3</b></li><li><b>4</b></li><li><b>5</b></li><li><b>6</b></li><li><b>下一页</b></li></ul></div>"}