{"id":8423,"title":"《十月围城》曝剧照 钟汉良由车夫变少爷","keywords":"十月围城,剧照,钟汉良,车夫,少爷,近日,电视剧,十月围城,曝光,","description":"近日，电视剧《十月围城》曝光了一组剧照，剧中的钟汉良由车夫摇身一边成为一位公子哥，然后与众女产生感情纠葛，剧情十分的引人注目. 近日，电视剧《十月围城》曝光了一组剧照，剧中的钟汉良由车夫摇身一边成为一位公子哥，然后与众女产生感情纠葛，剧","content":"<center><img src=\"/uploads/3d4a25ba049faa45e3358c44d950539e.jpg\"></center>\n\t\t\t\t\n\t\t\t\t\t\t\t\t\n\t\n\t近日，电视剧《十月围城》曝光了一组剧照，剧中的钟汉良由车夫摇身一边成为一位公子哥，然后与众女产生感情纠葛，剧情十分的引人注目。\n\n<div></div><div><ul><li><span>1</span></li><li><b>2</b></li><li><b>3</b></li><li><b>4</b></li><li><b>5</b></li><li><b>6</b></li><li><b>下一页</b></li></ul></div>"}