{"id":9451,"title":"李易峰和女友在泰国度假被拍：我有钱 我不穷游","keywords":"李易峰","description":"近日李易峰出席活动，被提问不工作的时候有什么爱好。李易峰平易近人地回答：看电影 去旅行 运动，差不多跟大家都一样。 但他很快就暴露了。当记者问了一句平时喜欢怎么旅游，跟团还是穷游时，峰峰给出了一个机智的笑容，逻辑缜密无可辩驳地回答：我这么有钱","content":"<p><strong>近日李易峰出席活动，被提问不工作的时候有什么爱好。李易峰平易近人地回答：“看电影、去旅行、运动，差不多跟大家都一样。”</strong></p><p><strong><img src=\"/uploads/d62ae9a05af371ae2df1e78925c38d9f.jpg\"></strong></p><p><strong>但他很快就暴露了。当记者问了一句平时喜欢怎么旅游，跟团还是穷游时，峰峰给出了一个机智的笑容，逻辑缜密无可辩驳地回答：“我这么有钱不可能穷游的。”可以说这是很耿直了。</strong></p><p><strong><img src=\"/uploads/ad906fa5f4ae05208dd0c86f4ae47f3e.jpg\"></strong></p><p><strong><img src=\"/uploads/79d2d663069e0358809b60af0f6266a8.jpg\"></strong></p><p><strong>翻了翻李易峰的微博，果然不是无边泳池，就是高山采冰，并且还要炫耀“你们上班我来度假”。</strong></p><p><strong><img src=\"/uploads/04b7e9a99d110a71329338cd70f523e4.jpg\"></strong></p><p><strong>我们再来说说李纯，在机场，一件白色T恤衫、一件粉红色外套、一条蓝色牛仔裤和一顶白帽子。整个人看上去很年轻，活泼可爱。</strong></p><p><strong><img src=\"/uploads/655724b90a2b87ace35c217bf17037c0.jpg\"></strong></p><p><strong>再来看李易峰，穿了同样的外套也是一件白色的T恤衫，一条牛仔裤和一顶白帽子!这样的衣服和两个人的造型是否一样？</strong></p><p><strong><img src=\"/uploads/4ac19121db731357c6d90f0489b12881.jpg\"></strong></p><p><strong>除了情人的衣服外，也有朋友发现有两个人被怀疑去了泰国，这两个人在微博上已经接触了很长时间。</strong></p><p><strong><img src=\"/uploads/15b065aca1802e28eced3dc97f88e659.jpg\"></strong></p><div></div><div><ul></ul></div>"}