{"id":9886,"title":"木子美曝与路金波床上秘事 被讽丑人多作怪","keywords":"木子美,金波,床上,秘事,讽丑,人多,作怪,作家,木子美,曝光,她与,","description":"作家木子美在曝光了她与杨树鹏的关系之后，近日，又在微博大肆爆料她与路金波睡过，再次吸引很多人的关注，下面我们也来瞧瞧吧. 11月6日22时左右，微博认证为不加V的女作家木子美在微博爆料称自己和路金波睡过，其后路金波的太太演员赵子琪则发微博讽其丑人","content":"<p>\n\t　　作家木子美在曝光了她与杨树鹏的关系之后，近日，又在微博大肆爆料她与路金波睡过，再次吸引很多人的关注，下面我们也来瞧瞧吧。</p><p><img alt=\"木子美路金波\" src=\"/uploads/9325fa04187dd54faa21419fd25c528f.jpg\"></p><p>\n\t　　11月6日22时左右，微博认证为“不加V”的女作家木子美在微博爆料称自己和路金波睡过，其后路金波的太太演员赵子琪则发微博讽其丑人多作怪。木子美更在微博中称路金波喝多了以后更曾将自己和另一个女作家送给自己的好兄弟去睡被自己拒绝后又领到了路金波的床上，更有网友猜测路金波的好兄弟或为作家导演韩寒。</p><p>\n\t　　随后木子美更是连发微博称路金波在接受媒体采访时落井下石，说自己是他最大的失败品，让其损失百万。木子美称这位睡过一张床的“难兄难弟”曾写邮件要求自己放弃部分版税，而随后在接受采访时就将其推入一个无比尴尬的位置。</p><p>\n\t　　木子美微博原文：</p><p>\n\t　　今天赵子琪跟我撕逼了，本来还没觉得怎么，一堆她的粉我的粉也撕起来了。我突然就兴奋了，就想起10年前的夜晚，我和路金波为革命喝酒，喝得醉醺醺的，还要爬楼，累趴在床上，头还疼，都穿着衣服，礼貌性抱了一下，然后睡不着，又摸了一下，隔着秋裤都非常硬，然后他翻身压了我一下，然后又忍了，睡了。</p><p>\n\t　　断篇儿了，因为几乎每次见路金波都喝酒，我不知道这种介于工作伙伴和难兄难弟的私情是啥，这么说吧，我和他睡一张床，也不难为情，我洗澡，他进来看一眼，我也不难为情。甚至有一回，他貌似打算把我和另一个女作者送给某个他兄弟睡睡，我不配合，他就把我领回去跟他睡。我们之间绝对是赤诚的，但没啪。</p><p>\n\t　　正因为他以难兄难弟的感情哄了我那么久，写邮件让我放弃部分版税时，我二话不说就放弃。后来他在媒体上接受采访，说做我的书让他亏了上百万，说我是他最失败的作者，我才很生气。哥们，我们也算睡过一张床的，也算和你一起看过夕阳的。那些钱不要就不要，不给就不给了。我受那么多苦，你怎能落井下石。</p><div></div><div><ul></ul></div>"}